{
  "pair_address": "7edPFT7WF37F1xgAUbSWsvBJ2MNX5BtaiE1czt2ggxtX",
  "token_address": "3HFVVmGGto5h3LG6C9yMVJ1XgGR6jynDfK8umKkPpump",
  "symbol": "pow",
  "name": "proof of work solana memecoin",
  "price": "0.00007770",
  "liquidity": 21253.71,
  "mcap": 77709,
  "volume_24h": 214479.5,
  "price_change_24h": 135,
  "buys_24h": 2284,
  "sells_24h": 1941,
  "buy_sell_ratio": 1.1767130345182895,
  "dex": "pumpswap",
  "analyzed_at": "2026-04-07T04:21:15.072037",
  "signals": [
    "RAPID_MOVE"
  ]
}